{
  "error": [
    "EQuery:Invalid asset pair",
    "EQuery:Invalid asset pair"
  ],
  "result": {
    "BCHEUR": {
      "a": [
        "202.200000",
        "39",
        "39.000"
      ],
      "b": [
        "202.000000",
        "4",
        "4.000"
      ],
      "c": [
        "201.900000",
        "1.33000000"
      ],
      "h": [
        "203.500000",
        "205.400000"
      ],
      "l": [
        "196.400000",
        "194.500000"
      ],
      "o": "200.000000",
      "p": [
        "200.304327",
        "200.513807"
      ],
      "t": [
        364,
        2170
      ],
      "v": [
        "1029.23496808",
        "5893.22569033"
      ]
    },
    "BCHUSD": {
      "a": [
        "221.500000",
        "6",
        "6.000"
      ],
      "b": [
        "221.400000",
        "12",
        "12.000"
      ],
      "c": [
        "221.000000",
        "2.69351954"
      ],
      "h": [
        "224.200000",
        "227.300000"
      ],
      "l": [
        "216.300000",
        "214.800000"
      ],
      "o": "220.400000",
      "p": [
        "220.298505",
        "221.213556"
      ],
      "t": [
        633,
        2795
      ],
      "v": [
        "1501.88675051",
        "7969.87952344"
      ]
    },
    "BCHXBT": {
      "a": [
        "0.03423000",
        "1",
        "1.000"
      ],
      "b": [
        "0.03418000",
        "2",
        "2.000"
      ],
      "c": [
        "0.03420000",
        "0.00190011"
      ],
      "h": [
        "0.03448000",
        "0.03520000"
      ],
      "l": [
        "0.03381000",
        "0.03381000"
      ],
      "o": "0.03446000",
      "p": [
        "0.03412595",
        "0.03403025"
      ],
      "t": [
        220,
        566
      ],
      "v": [
        "323.59408978",
        "776.14117551"
      ]
    },
    "DASHEUR": {
      "a": [
        "59.868000",
        "3",
        "3.000"
      ],
      "b": [
        "59.694000",
        "8",
        "8.000"
      ],
      "c": [
        "59.725000",
        "0.00000681"
      ],
      "h": [
        "60.364000",
        "61.520000"
      ],
      "l": [
        "58.663000",
        "58.074000"
      ],
      "o": "59.722000",
      "p": [
        "59.465900",
        "59.720331"
      ],
      "t": [
        151,
        705
      ],
      "v": [
        "772.24007305",
        "3512.98110974"
      ]
    },
    "DASHUSD": {
      "a": [
        "65.620000",
        "11",
        "11.000"
      ],
      "b": [
        "65.416000",
        "11",
        "11.000"
      ],
      "c": [
        "65.100000",
        "8.01473975"
      ],
      "h": [
        "66.387000",
        "67.521000"
      ],
      "l": [
        "64.516000",
        "64.154000"
      ],
      "o": "66.000000",
      "p": [
        "64.914718",
        "66.320547"
      ],
      "t": [
        79,
        327
      ],
      "v": [
        "326.98944012",
        "1726.10341341"
      ]
    },
    "DASHXBT": {
      "a": [
        "0.01014000",
        "15",
        "15.000"
      ],
      "b": [
        "0.01011000",
        "5",
        "5.000"
      ],
      "c": [
        "0.01014000",
        "0.50830199"
      ],
      "h": [
        "0.01031000",
        "0.01058000"
      ],
      "l": [
        "0.01006000",
        "0.01006000"
      ],
      "o": "0.01031000",
      "p": [
        "0.01013120",
        "0.01014906"
      ],
      "t": [
        99,
        443
      ],
      "v": [
        "62.69399029",
        "562.13124196"
      ]
    },
    "EOSETH": {
      "a": [
        "0.01675300",
        "119",
        "119.000"
      ],
      "b": [
        "0.01671100",
        "119",
        "119.000"
      ],
      "c": [
        "0.01671000",
        "43.90753890"
      ],
      "h": [
        "0.01686000",
        "0.01686300"
      ],
      "l": [
        "0.01670200",
        "0.01670200"
      ],
      "o": "0.01672500",
      "p": [
        "0.01675664",
        "0.01662181"
      ],
      "t": [
        18,
        31
      ],
      "v": [
        "994.70256299",
        "1951.22124401"
      ]
    },
    "EOSXBT": {
      "a": [
        "0.00034330",
        "118",
        "118.000"
      ],
      "b": [
        "0.00034260",
        "118",
        "118.000"
      ],
      "c": [
        "0.00034320",
        "332.34162847"
      ],
      "h": [
        "0.00034750",
        "0.00035050"
      ],
      "l": [
        "0.00034300",
        "0.00034300"
      ],
      "o": "0.00034750",
      "p": [
        "0.00034483",
        "-0.00013022"
      ],
      "t": [
        28,
        82
      ],
      "v": [
        "5843.57638384",
        "7388.33436692"
      ]
    },
    "GNOETH": {
      "a": [
        "0.07500000",
        "772",
        "772.000"
      ],
      "b": [
        "0.07480000",
        "34",
        "34.000"
      ],
      "c": [
        "0.07450000",
        "9.97406748"
      ],
      "h": [
        "0.07490000",
        "0.07500000"
      ],
      "l": [
        "0.07400000",
        "0.07310000"
      ],
      "o": "0.07410000",
      "p": [
        "0.07473792",
        "0.07418975"
      ],
      "t": [
        20,
        84
      ],
      "v": [
        "166.59040610",
        "830.11819315"
      ]
    },
    "GNOXBT": {
      "a": [
        "0.00154000",
        "36",
        "36.000"
      ],
      "b": [
        "0.00153000",
        "79",
        "79.000"
      ],
      "c": [
        "0.00153000",
        "2.76436249"
      ],
      "h": [
        "0.00153000",
        "0.00157000"
      ],
      "l": [
        "0.00153000",
        "0.00150000"
      ],
      "o": "0.00153000",
      "p": [
        "0.00153000",
        "0.00153000"
      ],
      "t": [
        9,
        76
      ],
      "v": [
        "122.79306157",
        "786.94490389"
      ]
    },
    "USDTZUSD": {
      "a": [
        "1.00220000",
        "11203",
        "11203.000"
      ],
      "b": [
        "1.00200000",
        "54389",
        "54389.000"
      ],
      "c": [
        "1.00220000",
        "52.74444566"
      ],
      "h": [
        "1.00240000",
        "1.00480000"
      ],
      "l": [
        "1.00100000",
        "1.00100000"
      ],
      "o": "1.00220000",
      "p": [
        "1.00160393",
        "1.00219051"
      ],
      "t": [
        1266,
        4598
      ],
      "v": [
        "1068002.29185391",
        "3924787.95806885"
      ]
    },
    "XETCXETH": {
      "a": [
        "0.03737000",
        "51",
        "51.000"
      ],
      "b": [
        "0.03724900",
        "128",
        "128.000"
      ],
      "c": [
        "0.03737000",
        "0.30000000"
      ],
      "h": [
        "0.03739700",
        "0.03767000"
      ],
      "l": [
        "0.03715700",
        "0.03692800"
      ],
      "o": "0.03739400",
      "p": [
        "0.03735759",
        "0.03727366"
      ],
      "t": [
        14,
        50
      ],
      "v": [
        "107.53615372",
        "400.34166673"
      ]
    },
    "XETCXXBT": {
      "a": [
        "0.00076500",
        "80",
        "80.000"
      ],
      "b": [
        "0.00076400",
        "675",
        "675.000"
      ],
      "c": [
        "0.00076300",
        "50.00000000"
      ],
      "h": [
        "0.00077400",
        "0.00078800"
      ],
      "l": [
        "0.00076200",
        "0.00076200"
      ],
      "o": "0.00077300",
      "p": [
        "0.00077033",
        "0.00074486"
      ],
      "t": [
        34,
        256
      ],
      "v": [
        "1478.62060903",
        "14934.15362852"
      ]
    },
    "XETCZEUR": {
      "a": [
        "4.53200000",
        "529",
        "529.000"
      ],
      "b": [
        "4.51600000",
        "458",
        "458.000"
      ],
      "c": [
        "4.54000000",
        "64.89999924"
      ],
      "h": [
        "4.54000000",
        "4.58000000"
      ],
      "l": [
        "4.46600000",
        "4.45400000"
      ],
      "o": "4.49300000",
      "p": [
        "4.50700856",
        "4.51868601"
      ],
      "t": [
        74,
        331
      ],
      "v": [
        "3980.07934993",
        "17783.62530143"
      ]
    },
    "XETCZUSD": {
      "a": [
        "4.96300000",
        "110",
        "110.000"
      ],
      "b": [
        "4.95200000",
        "75",
        "75.000"
      ],
      "c": [
        "4.95000000",
        "0.80192357"
      ],
      "h": [
        "4.99800000",
        "5.04500000"
      ],
      "l": [
        "4.91200000",
        "4.89600000"
      ],
      "o": "4.93800000",
      "p": [
        "4.93418894",
        "4.97008894"
      ],
      "t": [
        66,
        220
      ],
      "v": [
        "4189.54606463",
        "11187.69486313"
      ]
    },
    "XETHXXBT": {
      "a": [
        "0.020510",
        "41",
        "41.000"
      ],
      "b": [
        "0.020500",
        "8",
        "8.000"
      ],
      "c": [
        "0.020520",
        "2.29685405"
      ],
      "h": [
        "0.020670",
        "0.021060"
      ],
      "l": [
        "0.020400",
        "0.020400"
      ],
      "o": "0.020670",
      "p": [
        "0.020491",
        "-0.081963"
      ],
      "t": [
        430,
        1572
      ],
      "v": [
        "1423.80305347",
        "4697.31447657"
      ]
    },
    "XETHZGBP": {
      "a": [
        "108.12000",
        "7",
        "7.000"
      ],
      "b": [
        "107.80000",
        "38",
        "38.000"
      ],
      "c": [
        "108.41000",
        "0.00002682"
      ],
      "h": [
        "108.50000",
        "111.30000"
      ],
      "l": [
        "106.04000",
        "106.04000"
      ],
      "o": "108.50000",
      "p": [
        "107.22610",
        "108.49420"
      ],
      "t": [
        16,
        105
      ],
      "v": [
        "44.07561380",
        "411.65182294"
      ]
    },
    "XETHZJPY": {
      "a": [
        "14469.00000",
        "3",
        "3.000"
      ],
      "b": [
        "14393.00000",
        "9",
        "9.000"
      ],
      "c": [
        "14460.00000",
        "1.80132000"
      ],
      "h": [
        "14497.00000",
        "14546.00000"
      ],
      "l": [
        "14234.00000",
        "14209.00000"
      ],
      "o": "14497.00000",
      "p": [
        "14308.33656",
        "14334.88675"
      ],
      "t": [
        3,
        30
      ],
      "v": [
        "5.52564785",
        "123.48955128"
      ]
    },
    "XETHZUSD": {
      "a": [
        "132.79000",
        "3",
        "3.000"
      ],
      "b": [
        "132.71000",
        "10",
        "10.000"
      ],
      "c": [
        "132.82000",
        "0.04746666"
      ],
      "h": [
        "134.27000",
        "135.47000"
      ],
      "l": [
        "130.35000",
        "130.35000"
      ],
      "o": "132.28000",
      "p": [
        "132.06706",
        "130.63558"
      ],
      "t": [
        1243,
        7601
      ],
      "v": [
        "8441.33266877",
        "49620.90356944"
      ]
    },
    "XLTCXXBT": {
      "a": [
        "0.00605700",
        "13",
        "13.000"
      ],
      "b": [
        "0.00604900",
        "13",
        "13.000"
      ],
      "c": [
        "0.00605100",
        "0.00001842"
      ],
      "h": [
        "0.00608300",
        "0.00616500"
      ],
      "l": [
        "0.00598000",
        "0.00598000"
      ],
      "o": "0.00608300",
      "p": [
        "0.00601469",
        "0.00558082"
      ],
      "t": [
        98,
        323
      ],
      "v": [
        "1205.53259858",
        "2545.98530497"
      ]
    },
    "XLTCZEUR": {
      "a": [
        "35.78000",
        "420",
        "420.000"
      ],
      "b": [
        "35.75000",
        "62",
        "62.000"
      ],
      "c": [
        "35.71000",
        "5.58614674"
      ],
      "h": [
        "35.78000",
        "36.00000"
      ],
      "l": [
        "34.91000",
        "34.84000"
      ],
      "o": "35.40000",
      "p": [
        "35.33519",
        "34.96792"
      ],
      "t": [
        267,
        1135
      ],
      "v": [
        "2234.76998194",
        "17002.04411756"
      ]
    },
    "XLTCZUSD": {
      "a": [
        "39.23000",
        "12",
        "12.000"
      ],
      "b": [
        "39.21000",
        "67",
        "67.000"
      ],
      "c": [
        "39.21000",
        "0.00000670"
      ],
      "h": [
        "39.36000",
        "39.77000"
      ],
      "l": [
        "38.44000",
        "38.44000"
      ],
      "o": "38.99000",
      "p": [
        "38.87950",
        "38.54911"
      ],
      "t": [
        252,
        957
      ],
      "v": [
        "4112.71761872",
        "15403.07597860"
      ]
    },
    "XMLNXETH": {
      "a": [
        "0.02029000",
        "4",
        "4.000"
      ],
      "b": [
        "0.01985000",
        "20",
        "20.000"
      ],
      "c": [
        "0.02034000",
        "86.50000000"
      ],
      "h": [
        "0.02050000",
        "0.02129000"
      ],
      "l": [
        "0.01860000",
        "0.01860000"
      ],
      "o": "0.01982000",
      "p": [
        "0.01993756",
        "0.01993759"
      ],
      "t": [
        59,
        81
      ],
      "v": [
        "1745.87186407",
        "2495.01868361"
      ]
    },
    "XMLNXXBT": {
      "a": [
        "0.00041600",
        "50",
        "50.000"
      ],
      "b": [
        "0.00040800",
        "1",
        "1.000"
      ],
      "c": [
        "0.00041800",
        "4.37697152"
      ],
      "h": [
        "0.00042100",
        "0.00043800"
      ],
      "l": [
        "0.00040100",
        "0.00040100"
      ],
      "o": "0.00041900",
      "p": [
        "0.00041433",
        "0.00039619"
      ],
      "t": [
        30,
        50
      ],
      "v": [
        "779.17428301",
        "1253.80068344"
      ]
    },
    "XREPXETH": {
      "a": [
        "0.080710",
        "33",
        "33.000"
      ],
      "b": [
        "0.080350",
        "24",
        "24.000"
      ],
      "c": [
        "0.080110",
        "6.79300000"
      ],
      "h": [
        "0.080120",
        "0.080120"
      ],
      "l": [
        "0.074780",
        "0.074770"
      ],
      "o": "0.074780",
      "p": [
        "0.078207",
        "0.069506"
      ],
      "t": [
        27,
        50
      ],
      "v": [
        "293.38351664",
        "551.52576469"
      ]
    },
    "XREPXXBT": {
      "a": [
        "0.001654",
        "75",
        "75.000"
      ],
      "b": [
        "0.001647",
        "5",
        "5.000"
      ],
      "c": [
        "0.001647",
        "1.47103600"
      ],
      "h": [
        "0.001647",
        "0.001647"
      ],
      "l": [
        "0.001547",
        "0.001530"
      ],
      "o": "0.001548",
      "p": [
        "0.001599",
        "-0.000704"
      ],
      "t": [
        141,
        315
      ],
      "v": [
        "1945.72025249",
        "5795.48026486"
      ]
    },
    "XREPZEUR": {
      "a": [
        "9.76400",
        "51",
        "51.000"
      ],
      "b": [
        "9.72600",
        "26",
        "26.000"
      ],
      "c": [
        "9.73000",
        "30.50000000"
      ],
      "h": [
        "9.73400",
        "9.73400"
      ],
      "l": [
        "9.06100",
        "8.89000"
      ],
      "o": "9.06100",
      "p": [
        "9.40281",
        "9.20122"
      ],
      "t": [
        257,
        492
      ],
      "v": [
        "8571.23166717",
        "12785.07777178"
      ]
    },
    "XXBTZCAD": {
      "a": [
        "9241.40000",
        "1",
        "1.000"
      ],
      "b": [
        "9219.40000",
        "1",
        "1.000"
      ],
      "c": [
        "9212.00000",
        "0.02782907"
      ],
      "h": [
        "9302.00000",
        "9375.40000"
      ],
      "l": [
        "9103.90000",
        "8932.30000"
      ],
      "o": "9120.10000",
      "p": [
        "9186.33636",
        "9137.18328"
      ],
      "t": [
        150,
        637
      ],
      "v": [
        "17.17592862",
        "77.46387545"
      ]
    },
    "XXBTZEUR": {
      "a": [
        "5913.00000",
        "3",
        "3.000"
      ],
      "b": [
        "5912.90000",
        "1",
        "1.000"
      ],
      "c": [
        "5913.00000",
        "0.12421202"
      ],
      "h": [
        "5941.90000",
        "5995.90000"
      ],
      "l": [
        "5797.70000",
        "5677.80000"
      ],
      "o": "5804.60000",
      "p": [
        "5878.48223",
        "5804.48266"
      ],
      "t": [
        7180,
        33845
      ],
      "v": [
        "1486.34725211",
        "9174.79688661"
      ]
    },
    "XXBTZGBP": {
      "a": [
        "5271.40000",
        "1",
        "1.000"
      ],
      "b": [
        "5257.10000",
        "1",
        "1.000"
      ],
      "c": [
        "5292.30000",
        "0.00600000"
      ],
      "h": [
        "5307.00000",
        "5332.90000"
      ],
      "l": [
        "5202.20000",
        "5100.20000"
      ],
      "o": "5202.20000",
      "p": [
        "5272.70626",
        "5198.16554"
      ],
      "t": [
        87,
        401
      ],
      "v": [
        "18.14543775",
        "76.66103250"
      ]
    },
    "XXBTZJPY": {
      "a": [
        "706332.000",
        "1",
        "1.000"
      ],
      "b": [
        "702530.000",
        "1",
        "1.000"
      ],
      "c": [
        "697860.000",
        "0.00352000"
      ],
      "h": [
        "702754.000",
        "713828.000"
      ],
      "l": [
        "695704.000",
        "681594.000"
      ],
      "o": "702754.000",
      "p": [
        "698479.967",
        "696715.042"
      ],
      "t": [
        11,
        61
      ],
      "v": [
        "0.20349148",
        "1.32198425"
      ]
    },
    "XXBTZUSD": {
      "a": [
        "6476.70000",
        "52",
        "52.000"
      ],
      "b": [
        "6475.00000",
        "1",
        "1.000"
      ],
      "c": [
        "6475.40000",
        "0.00065611"
      ],
      "h": [
        "6525.00000",
        "6640.00000"
      ],
      "l": [
        "6384.20000",
        "6257.30000"
      ],
      "o": "6403.20000",
      "p": [
        "6450.41786",
        "6429.74521"
      ],
      "t": [
        5919,
        24678
      ],
      "v": [
        "2384.96840007",
        "9348.90373931"
      ]
    },
    "XXDGXXBT": {
      "a": [
        "0.000000290",
        "15257614",
        "15257614.000"
      ],
      "b": [
        "0.000000280",
        "10285593",
        "10285593.000"
      ],
      "c": [
        "0.000000280",
        "9972.07261121"
      ],
      "h": [
        "0.000000290",
        "0.000000290"
      ],
      "l": [
        "0.000000280",
        "0.000000280"
      ],
      "o": "0.000000290",
      "p": [
        "0.000000280",
        "-0.000010003"
      ],
      "t": [
        14,
        32
      ],
      "v": [
        "259104.09901731",
        "1587863.01241508"
      ]
    },
    "XXLMXXBT": {
      "a": [
        "0.000006270",
        "6247",
        "6247.000"
      ],
      "b": [
        "0.000006260",
        "91799",
        "91799.000"
      ],
      "c": [
        "0.000006260",
        "0.00000026"
      ],
      "h": [
        "0.000006280",
        "0.000006390"
      ],
      "l": [
        "0.000006220",
        "0.000006170"
      ],
      "o": "0.000006240",
      "p": [
        "0.000006259",
        "-0.000015759"
      ],
      "t": [
        37,
        129
      ],
      "v": [
        "76030.88011696",
        "272471.55164393"
      ]
    },
    "XXMRXXBT": {
      "a": [
        "0.00738900",
        "7",
        "7.000"
      ],
      "b": [
        "0.00737600",
        "15",
        "15.000"
      ],
      "c": [
        "0.00739100",
        "2.58800000"
      ],
      "h": [
        "0.00743800",
        "0.00750000"
      ],
      "l": [
        "0.00722600",
        "0.00721600"
      ],
      "o": "0.00727500",
      "p": [
        "0.00734009",
        "0.00725475"
      ],
      "t": [
        149,
        594
      ],
      "v": [
        "682.24021379",
        "4079.18675409"
      ]
    },
    "XXMRZEUR": {
      "a": [
        "43.71000000",
        "7",
        "7.000"
      ],
      "b": [
        "43.63000000",
        "40",
        "40.000"
      ],
      "c": [
        "43.70000000",
        "0.45071000"
      ],
      "h": [
        "43.98000000",
        "43.98000000"
      ],
      "l": [
        "42.30000000",
        "42.30000000"
      ],
      "o": "42.30000000",
      "p": [
        "43.12211987",
        "42.80288831"
      ],
      "t": [
        173,
        963
      ],
      "v": [
        "1292.62460341",
        "8081.22856755"
      ]
    },
    "XXMRZUSD": {
      "a": [
        "47.85000000",
        "13",
        "13.000"
      ],
      "b": [
        "47.77000000",
        "24",
        "24.000"
      ],
      "c": [
        "47.96000000",
        "0.24981815"
      ],
      "h": [
        "48.06000000",
        "48.06000000"
      ],
      "l": [
        "46.59000000",
        "46.59000000"
      ],
      "o": "46.60000000",
      "p": [
        "47.13425207",
        "47.14719896"
      ],
      "t": [
        263,
        813
      ],
      "v": [
        "3418.46110575",
        "6212.49374854"
      ]
    },
    "XXRPXXBT": {
      "a": [
        "0.000026780",
        "3444",
        "3444.000"
      ],
      "b": [
        "0.000026750",
        "5220",
        "5220.000"
      ],
      "c": [
        "0.000026720",
        "224.55089820"
      ],
      "h": [
        "0.000026820",
        "0.000027510"
      ],
      "l": [
        "0.000026560",
        "0.000026470"
      ],
      "o": "0.000026800",
      "p": [
        "0.000026699",
        "-0.000005919"
      ],
      "t": [
        115,
        501
      ],
      "v": [
        "137626.84225176",
        "929576.72265994"
      ]
    },
    "XXRPZEUR": {
      "a": [
        "0.15812000",
        "276859",
        "276859.000"
      ],
      "b": [
        "0.15805000",
        "819",
        "819.000"
      ],
      "c": [
        "0.15812000",
        "1252.53036437"
      ],
      "h": [
        "0.15829000",
        "0.15940000"
      ],
      "l": [
        "0.15510000",
        "0.15500000"
      ],
      "o": "0.15543000",
      "p": [
        "0.15661420",
        "0.15663335"
      ],
      "t": [
        595,
        3053
      ],
      "v": [
        "2612210.00135461",
        "10976485.30019316"
      ]
    },
    "XXRPZUSD": {
      "a": [
        "0.17337000",
        "6532",
        "6532.000"
      ],
      "b": [
        "0.17332000",
        "10000",
        "10000.000"
      ],
      "c": [
        "0.17299000",
        "724.52000000"
      ],
      "h": [
        "0.17366000",
        "0.17595000"
      ],
      "l": [
        "0.17058000",
        "0.17058000"
      ],
      "o": "0.17137000",
      "p": [
        "0.17213714",
        "0.17241451"
      ],
      "t": [
        500,
        2284
      ],
      "v": [
        "2839954.78561099",
        "12296769.73180064"
      ]
    },
    "XZECXXBT": {
      "a": [
        "0.004750",
        "9",
        "9.000"
      ],
      "b": [
        "0.004740",
        "16",
        "16.000"
      ],
      "c": [
        "0.004750",
        "8.42105263"
      ],
      "h": [
        "0.004780",
        "0.004930"
      ],
      "l": [
        "0.004730",
        "0.004730"
      ],
      "o": "0.004780",
      "p": [
        "0.004744",
        "-0.003561"
      ],
      "t": [
        42,
        202
      ],
      "v": [
        "210.87051128",
        "1038.28984559"
      ]
    },
    "XZECZEUR": {
      "a": [
        "28.06700",
        "2",
        "2.000"
      ],
      "b": [
        "28.00000",
        "110",
        "110.000"
      ],
      "c": [
        "28.05100",
        "2.10000000"
      ],
      "h": [
        "28.22000",
        "28.63300"
      ],
      "l": [
        "27.57100",
        "27.05300"
      ],
      "o": "27.98700",
      "p": [
        "28.06595",
        "27.89564"
      ],
      "t": [
        86,
        382
      ],
      "v": [
        "1269.13947503",
        "3311.88325179"
      ]
    },
    "XZECZUSD": {
      "a": [
        "30.76000",
        "9",
        "9.000"
      ],
      "b": [
        "30.65000",
        "31",
        "31.000"
      ],
      "c": [
        "30.78000",
        "0.26545986"
      ],
      "h": [
        "31.00000",
        "31.64000"
      ],
      "l": [
        "30.36000",
        "30.13000"
      ],
      "o": "30.78000",
      "p": [
        "30.67695",
        "30.68431"
      ],
      "t": [
        24,
        269
      ],
      "v": [
        "205.68923755",
        "2224.23954551"
      ]
    }
  }
}