{
  "error": [
    "EQuery:Invalid asset pair",
    "EQuery:Invalid asset pair"
  ],
  "result": {
    "BCHEUR": {
      "a": [
        "223.800000",
        "4",
        "4.000"
      ],
      "b": [
        "223.500000",
        "2",
        "2.000"
      ],
      "c": [
        "223.800000",
        "6.05315416"
      ],
      "h": [
        "224.500000",
        "229.200000"
      ],
      "l": [
        "213.100000",
        "207.200000"
      ],
      "o": "214.000000",
      "p": [
        "220.193750",
        "218.101158"
      ],
      "t": [
        1128,
        4815
      ],
      "v": [
        "3763.38983119",
        "14500.02404948"
      ]
    },
    "BCHUSD": {
      "a": [
        "241.400000",
        "15",
        "15.000"
      ],
      "b": [
        "241.300000",
        "3",
        "3.000"
      ],
      "c": [
        "241.500000",
        "0.31237562"
      ],
      "h": [
        "245.100000",
        "249.200000"
      ],
      "l": [
        "231.100000",
        "225.300000"
      ],
      "o": "232.100000",
      "p": [
        "238.957510",
        "236.940822"
      ],
      "t": [
        1005,
        5645
      ],
      "v": [
        "3470.49508533",
        "16084.38938292"
      ]
    },
    "BCHXBT": {
      "a": [
        "0.03444000",
        "3",
        "3.000"
      ],
      "b": [
        "0.03439000",
        "3",
        "3.000"
      ],
      "c": [
        "0.03439000",
        "0.00250332"
      ],
      "h": [
        "0.03486000",
        "0.03486000"
      ],
      "l": [
        "0.03407000",
        "0.03387000"
      ],
      "o": "0.03414000",
      "p": [
        "0.03448242",
        "0.03404433"
      ],
      "t": [
        252,
        809
      ],
      "v": [
        "302.24909699",
        "838.40361692"
      ]
    },
    "DASHEUR": {
      "a": [
        "64.963000",
        "4",
        "4.000"
      ],
      "b": [
        "64.800000",
        "8",
        "8.000"
      ],
      "c": [
        "64.800000",
        "0.30800000"
      ],
      "h": [
        "65.254000",
        "66.000000"
      ],
      "l": [
        "62.267000",
        "60.501000"
      ],
      "o": "62.533000",
      "p": [
        "64.121660",
        "63.425053"
      ],
      "t": [
        295,
        1262
      ],
      "v": [
        "1126.69720289",
        "4879.47888733"
      ]
    },
    "DASHUSD": {
      "a": [
        "70.085000",
        "9",
        "9.000"
      ],
      "b": [
        "69.880000",
        "8",
        "8.000"
      ],
      "c": [
        "69.208000",
        "24.64797310"
      ],
      "h": [
        "70.143000",
        "71.727000"
      ],
      "l": [
        "67.234000",
        "65.717000"
      ],
      "o": "67.234000",
      "p": [
        "68.675611",
        "68.732206"
      ],
      "t": [
        135,
        906
      ],
      "v": [
        "580.11009832",
        "3554.18798953"
      ]
    },
    "DASHXBT": {
      "a": [
        "0.00999000",
        "4",
        "4.000"
      ],
      "b": [
        "0.00996000",
        "10",
        "10.000"
      ],
      "c": [
        "0.01000000",
        "0.06459012"
      ],
      "h": [
        "0.01019000",
        "0.01019000"
      ],
      "l": [
        "0.00993000",
        "0.00980000"
      ],
      "o": "0.00993000",
      "p": [
        "0.01009750",
        "0.00983381"
      ],
      "t": [
        228,
        467
      ],
      "v": [
        "307.43259095",
        "558.03376283"
      ]
    },
    "EOSETH": {
      "a": [
        "0.01623300",
        "106",
        "106.000"
      ],
      "b": [
        "0.01618400",
        "19",
        "19.000"
      ],
      "c": [
        "0.01623500",
        "12.59141200"
      ],
      "h": [
        "0.01632700",
        "0.01676100"
      ],
      "l": [
        "0.01623500",
        "0.01611100"
      ],
      "o": "0.01625200",
      "p": [
        "0.01628098",
        "0.01656691"
      ],
      "t": [
        15,
        67
      ],
      "v": [
        "512.40469368",
        "9532.15597412"
      ]
    },
    "EOSXBT": {
      "a": [
        "0.00033880",
        "108",
        "108.000"
      ],
      "b": [
        "0.00033820",
        "108",
        "108.000"
      ],
      "c": [
        "0.00033900",
        "19.67607350"
      ],
      "h": [
        "0.00034130",
        "0.00035060"
      ],
      "l": [
        "0.00033780",
        "0.00033600"
      ],
      "o": "0.00033850",
      "p": [
        "0.00033957",
        "0.00019997"
      ],
      "t": [
        59,
        235
      ],
      "v": [
        "2917.79923653",
        "24738.35774961"
      ]
    },
    "GNOETH": {
      "a": [
        "0.07230000",
        "38",
        "38.000"
      ],
      "b": [
        "0.07200000",
        "40",
        "40.000"
      ],
      "c": [
        "0.07210000",
        "5.00000000"
      ],
      "h": [
        "0.07290000",
        "0.07320000"
      ],
      "l": [
        "0.07160000",
        "0.07040000"
      ],
      "o": "0.07290000",
      "p": [
        "0.07196466",
        "0.07185900"
      ],
      "t": [
        34,
        228
      ],
      "v": [
        "295.05801537",
        "1735.10011801"
      ]
    },
    "GNOXBT": {
      "a": [
        "0.00151000",
        "77",
        "77.000"
      ],
      "b": [
        "0.00150000",
        "38",
        "38.000"
      ],
      "c": [
        "0.00149000",
        "0.00001899"
      ],
      "h": [
        "0.00152000",
        "0.00155000"
      ],
      "l": [
        "0.00149000",
        "0.00147000"
      ],
      "o": "0.00151000",
      "p": [
        "0.00149742",
        "0.00148790"
      ],
      "t": [
        40,
        168
      ],
      "v": [
        "155.99554422",
        "1130.05584988"
      ]
    },
    "USDTZUSD": {
      "a": [
        "1.00140000",
        "979",
        "979.000"
      ],
      "b": [
        "1.00120000",
        "5620",
        "5620.000"
      ],
      "c": [
        "1.00140000",
        "1566.31326265"
      ],
      "h": [
        "1.00220000",
        "1.00290000"
      ],
      "l": [
        "1.00050000",
        "1.00050000"
      ],
      "o": "1.00050000",
      "p": [
        "1.00108562",
        "1.00124915"
      ],
      "t": [
        2191,
        7516
      ],
      "v": [
        "1312033.39764720",
        "5662515.13105142"
      ]
    },
    "XETCXETH": {
      "a": [
        "0.03587900",
        "48",
        "48.000"
      ],
      "b": [
        "0.03569300",
        "8",
        "8.000"
      ],
      "c": [
        "0.03577500",
        "0.31600364"
      ],
      "h": [
        "0.03654900",
        "0.03699500"
      ],
      "l": [
        "0.03577500",
        "0.03558900"
      ],
      "o": "0.03580200",
      "p": [
        "0.03627860",
        "0.03603546"
      ],
      "t": [
        6,
        75
      ],
      "v": [
        "81.84321579",
        "712.32443060"
      ]
    },
    "XETCXXBT": {
      "a": [
        "0.00074700",
        "48",
        "48.000"
      ],
      "b": [
        "0.00074500",
        "290",
        "290.000"
      ],
      "c": [
        "0.00074400",
        "2.62032017"
      ],
      "h": [
        "0.00076400",
        "0.00076400"
      ],
      "l": [
        "0.00074400",
        "0.00073600"
      ],
      "o": "0.00074800",
      "p": [
        "0.00075413",
        "0.00064268"
      ],
      "t": [
        42,
        211
      ],
      "v": [
        "793.27323475",
        "4462.25736944"
      ]
    },
    "XETCZEUR": {
      "a": [
        "4.85600000",
        "80",
        "80.000"
      ],
      "b": [
        "4.84100000",
        "80",
        "80.000"
      ],
      "c": [
        "4.85900000",
        "207.00000000"
      ],
      "h": [
        "4.86000000",
        "4.91500000"
      ],
      "l": [
        "4.68000000",
        "4.62100000"
      ],
      "o": "4.68000000",
      "p": [
        "4.79270493",
        "4.76352901"
      ],
      "t": [
        183,
        741
      ],
      "v": [
        "8075.99423468",
        "29458.35742345"
      ]
    },
    "XETCZUSD": {
      "a": [
        "5.23400000",
        "1",
        "1.000"
      ],
      "b": [
        "5.22300000",
        "50",
        "50.000"
      ],
      "c": [
        "5.20400000",
        "0.00000024"
      ],
      "h": [
        "5.23000000",
        "5.34500000"
      ],
      "l": [
        "5.08800000",
        "5.02600000"
      ],
      "o": "5.08800000",
      "p": [
        "5.18832135",
        "5.14234739"
      ],
      "t": [
        84,
        333
      ],
      "v": [
        "1799.29395804",
        "8352.69018776"
      ]
    },
    "XETHXXBT": {
      "a": [
        "0.020870",
        "4",
        "4.000"
      ],
      "b": [
        "0.020860",
        "18",
        "18.000"
      ],
      "c": [
        "0.020870",
        "0.00037500"
      ],
      "h": [
        "0.021000",
        "0.021100"
      ],
      "l": [
        "0.020760",
        "0.020440"
      ],
      "o": "0.020810",
      "p": [
        "0.020842",
        "-0.043407"
      ],
      "t": [
        1143,
        7070
      ],
      "v": [
        "1672.48189998",
        "7148.15875839"
      ]
    },
    "XETHZGBP": {
      "a": [
        "119.60000",
        "32",
        "32.000"
      ],
      "b": [
        "119.19000",
        "6",
        "6.000"
      ],
      "c": [
        "118.94000",
        "0.95211399"
      ],
      "h": [
        "118.94000",
        "120.81000"
      ],
      "l": [
        "115.17000",
        "110.92000"
      ],
      "o": "115.17000",
      "p": [
        "117.86550",
        "116.52301"
      ],
      "t": [
        20,
        171
      ],
      "v": [
        "33.23676041",
        "448.74481791"
      ]
    },
    "XETHZJPY": {
      "a": [
        "15972.00000",
        "8",
        "8.000"
      ],
      "b": [
        "15832.00000",
        "2",
        "2.000"
      ],
      "c": [
        "15785.00000",
        "0.30000000"
      ],
      "h": [
        "15790.00000",
        "15792.00000"
      ],
      "l": [
        "15180.00000",
        "14694.00000"
      ],
      "o": "15790.00000",
      "p": [
        "15614.73133",
        "15658.11883"
      ],
      "t": [
        18,
        23
      ],
      "v": [
        "18.76253909",
        "27.77356379"
      ]
    },
    "XETHZUSD": {
      "a": [
        "146.21000",
        "15",
        "15.000"
      ],
      "b": [
        "146.18000",
        "90",
        "90.000"
      ],
      "c": [
        "146.23000",
        "1.71432489"
      ],
      "h": [
        "146.90000",
        "150.70000"
      ],
      "l": [
        "140.54000",
        "136.47000"
      ],
      "o": "141.48000",
      "p": [
        "143.86093",
        "141.74872"
      ],
      "t": [
        3014,
        13002
      ],
      "v": [
        "21149.93045636",
        "94579.21776698"
      ]
    },
    "XLTCXXBT": {
      "a": [
        "0.00588400",
        "15",
        "15.000"
      ],
      "b": [
        "0.00587600",
        "15",
        "15.000"
      ],
      "c": [
        "0.00589000",
        "0.00883478"
      ],
      "h": [
        "0.00594000",
        "0.00597900"
      ],
      "l": [
        "0.00587000",
        "0.00585800"
      ],
      "o": "0.00587200",
      "p": [
        "0.00591221",
        "0.00547910"
      ],
      "t": [
        108,
        429
      ],
      "v": [
        "433.60861850",
        "2897.36795796"
      ]
    },
    "XLTCZEUR": {
      "a": [
        "38.19000",
        "1",
        "1.000"
      ],
      "b": [
        "38.16000",
        "22",
        "22.000"
      ],
      "c": [
        "38.19000",
        "2.59897729"
      ],
      "h": [
        "38.27000",
        "39.49000"
      ],
      "l": [
        "36.60000",
        "35.88000"
      ],
      "o": "36.76000",
      "p": [
        "37.63441",
        "37.26790"
      ],
      "t": [
        464,
        2487
      ],
      "v": [
        "5083.10411825",
        "25282.55436262"
      ]
    },
    "XLTCZUSD": {
      "a": [
        "41.20000",
        "60",
        "60.000"
      ],
      "b": [
        "41.17000",
        "268",
        "268.000"
      ],
      "c": [
        "41.18000",
        "0.00413817"
      ],
      "h": [
        "41.28000",
        "42.85000"
      ],
      "l": [
        "39.76000",
        "39.14000"
      ],
      "o": "39.96000",
      "p": [
        "40.55238",
        "40.47768"
      ],
      "t": [
        507,
        1867
      ],
      "v": [
        "6310.40438102",
        "28877.15396978"
      ]
    },
    "XMLNXETH": {
      "a": [
        "0.01928000",
        "5",
        "5.000"
      ],
      "b": [
        "0.01863000",
        "87",
        "87.000"
      ],
      "c": [
        "0.01901000",
        "4.71520181"
      ],
      "h": [
        "0.01929000",
        "0.01930000"
      ],
      "l": [
        "0.01876000",
        "0.01826000"
      ],
      "o": "0.01903000",
      "p": [
        "0.01892031",
        "0.01875782"
      ],
      "t": [
        17,
        69
      ],
      "v": [
        "131.61189604",
        "993.47915691"
      ]
    },
    "XMLNXXBT": {
      "a": [
        "0.00040100",
        "1",
        "1.000"
      ],
      "b": [
        "0.00039300",
        "50",
        "50.000"
      ],
      "c": [
        "0.00039200",
        "9.37972910"
      ],
      "h": [
        "0.00040100",
        "0.00042900"
      ],
      "l": [
        "0.00039000",
        "0.00038000"
      ],
      "o": "0.00039700",
      "p": [
        "0.00039484",
        "0.00038536"
      ],
      "t": [
        19,
        120
      ],
      "v": [
        "323.71288266",
        "2635.04199882"
      ]
    },
    "XREPXETH": {
      "a": [
        "0.068490",
        "26",
        "26.000"
      ],
      "b": [
        "0.068270",
        "105",
        "105.000"
      ],
      "c": [
        "0.068640",
        "3.60802211"
      ],
      "h": [
        "0.071350",
        "0.073710"
      ],
      "l": [
        "0.068640",
        "0.068640"
      ],
      "o": "0.071230",
      "p": [
        "0.070795",
        "0.067946"
      ],
      "t": [
        17,
        164
      ],
      "v": [
        "145.60228804",
        "1972.57385011"
      ]
    },
    "XREPXXBT": {
      "a": [
        "0.001428",
        "35",
        "35.000"
      ],
      "b": [
        "0.001427",
        "3",
        "3.000"
      ],
      "c": [
        "0.001427",
        "1.29599999"
      ],
      "h": [
        "0.001487",
        "0.001525"
      ],
      "l": [
        "0.001427",
        "0.001427"
      ],
      "o": "0.001478",
      "p": [
        "0.001454",
        "-0.001189"
      ],
      "t": [
        99,
        395
      ],
      "v": [
        "1294.06912541",
        "4816.94708506"
      ]
    },
    "XREPZEUR": {
      "a": [
        "9.29500",
        "48",
        "48.000"
      ],
      "b": [
        "9.27000",
        "23",
        "23.000"
      ],
      "c": [
        "9.29900",
        "10.75153209"
      ],
      "h": [
        "9.54000",
        "9.54000"
      ],
      "l": [
        "9.20300",
        "9.12100"
      ],
      "o": "9.25600",
      "p": [
        "9.41185",
        "9.32132"
      ],
      "t": [
        315,
        887
      ],
      "v": [
        "10234.75254676",
        "24412.32625752"
      ]
    },
    "XTZUSD": {
      "a": [
        "1.777700",
        "2000",
        "2000.000"
      ],
      "b": [
        "1.775800",
        "189",
        "189.000"
      ],
      "c": [
        "1.775600",
        "93.84119612"
      ],
      "h": [
        "1.777700",
        "1.799700"
      ],
      "l": [
        "1.661800",
        "1.640000"
      ],
      "o": "1.668500",
      "p": [
        "1.728178",
        "1.711610"
      ],
      "t": [
        810,
        4062
      ],
      "v": [
        "430089.37069892",
        "2004228.56490400"
      ]
    },
    "XXBTZCAD": {
      "a": [
        "9970.10000",
        "1",
        "1.000"
      ],
      "b": [
        "9957.30000",
        "1",
        "1.000"
      ],
      "c": [
        "9957.30000",
        "0.00000002"
      ],
      "h": [
        "9998.80000",
        "10256.30000"
      ],
      "l": [
        "9572.10000",
        "9454.90000"
      ],
      "o": "9663.10000",
      "p": [
        "9723.81569",
        "9795.97320"
      ],
      "t": [
        181,
        866
      ],
      "v": [
        "14.56582741",
        "77.66656189"
      ]
    },
    "XXBTZEUR": {
      "a": [
        "6499.70000",
        "4",
        "4.000"
      ],
      "b": [
        "6499.60000",
        "1",
        "1.000"
      ],
      "c": [
        "6499.60000",
        "0.03280388"
      ],
      "h": [
        "6526.40000",
        "6646.00000"
      ],
      "l": [
        "6201.00000",
        "6105.10000"
      ],
      "o": "6265.50000",
      "p": [
        "6400.70825",
        "6336.70191"
      ],
      "t": [
        14512,
        60206
      ],
      "v": [
        "3350.99932983",
        "15504.77520995"
      ]
    },
    "XXBTZGBP": {
      "a": [
        "5732.90000",
        "1",
        "1.000"
      ],
      "b": [
        "5714.80000",
        "1",
        "1.000"
      ],
      "c": [
        "5710.00000",
        "0.35000000"
      ],
      "h": [
        "5760.40000",
        "5879.00000"
      ],
      "l": [
        "5483.90000",
        "5391.30000"
      ],
      "o": "5497.00000",
      "p": [
        "5633.34989",
        "5595.71492"
      ],
      "t": [
        121,
        674
      ],
      "v": [
        "19.38235040",
        "77.59418082"
      ]
    },
    "XXBTZJPY": {
      "a": [
        "767803.000",
        "1",
        "1.000"
      ],
      "b": [
        "760050.000",
        "1",
        "1.000"
      ],
      "c": [
        "761246.000",
        "0.00000488"
      ],
      "h": [
        "766187.000",
        "769646.000"
      ],
      "l": [
        "742492.000",
        "719330.000"
      ],
      "o": "748768.000",
      "p": [
        "750661.533",
        "751936.474"
      ],
      "t": [
        83,
        115
      ],
      "v": [
        "2.36533948",
        "4.20130105"
      ]
    },
    "XXBTZUSD": {
      "a": [
        "7009.50000",
        "3",
        "3.000"
      ],
      "b": [
        "7006.90000",
        "2",
        "2.000"
      ],
      "c": [
        "7009.50000",
        "0.20000000"
      ],
      "h": [
        "7053.30000",
        "7269.00000"
      ],
      "l": [
        "6729.40000",
        "6632.60000"
      ],
      "o": "6800.50000",
      "p": [
        "6896.18195",
        "6887.04099"
      ],
      "t": [
        9861,
        42968
      ],
      "v": [
        "3974.33320626",
        "18336.27660750"
      ]
    },
    "XXDGXXBT": {
      "a": [
        "0.000000280",
        "15278415",
        "15278415.000"
      ],
      "b": [
        "0.000000270",
        "19547855",
        "19547855.000"
      ],
      "c": [
        "0.000000280",
        "100000.00000000"
      ],
      "h": [
        "0.000000280",
        "0.000000280"
      ],
      "l": [
        "0.000000270",
        "0.000000270"
      ],
      "o": "0.000000280",
      "p": [
        "0.000000273",
        "-0.000001925"
      ],
      "t": [
        18,
        50
      ],
      "v": [
        "853326.92785360",
        "7493332.53975609"
      ]
    },
    "XXLMXXBT": {
      "a": [
        "0.000006010",
        "308811",
        "308811.000"
      ],
      "b": [
        "0.000006000",
        "6450",
        "6450.000"
      ],
      "c": [
        "0.000006020",
        "35.30283164"
      ],
      "h": [
        "0.000006130",
        "0.000006140"
      ],
      "l": [
        "0.000005990",
        "0.000005930"
      ],
      "o": "0.000006060",
      "p": [
        "0.000006083",
        "0.000001006"
      ],
      "t": [
        63,
        290
      ],
      "v": [
        "254633.57012486",
        "1218875.12586376"
      ]
    },
    "XXMRXXBT": {
      "a": [
        "0.00773600",
        "23",
        "23.000"
      ],
      "b": [
        "0.00772500",
        "28",
        "28.000"
      ],
      "c": [
        "0.00773600",
        "0.00000587"
      ],
      "h": [
        "0.00779200",
        "0.00779200"
      ],
      "l": [
        "0.00744900",
        "0.00726500"
      ],
      "o": "0.00744900",
      "p": [
        "0.00766631",
        "0.00742795"
      ],
      "t": [
        1872,
        5398
      ],
      "v": [
        "2175.08153693",
        "5826.40305167"
      ]
    },
    "XXMRZEUR": {
      "a": [
        "50.22000000",
        "1",
        "1.000"
      ],
      "b": [
        "50.20000000",
        "7",
        "7.000"
      ],
      "c": [
        "50.11000000",
        "1.75226452"
      ],
      "h": [
        "50.30000000",
        "50.30000000"
      ],
      "l": [
        "46.44000000",
        "45.11000000"
      ],
      "o": "46.73000000",
      "p": [
        "49.19752944",
        "47.31721276"
      ],
      "t": [
        609,
        1958
      ],
      "v": [
        "3264.09281835",
        "11972.14815770"
      ]
    },
    "XXMRZUSD": {
      "a": [
        "54.19000000",
        "1",
        "1.000"
      ],
      "b": [
        "54.10000000",
        "7",
        "7.000"
      ],
      "c": [
        "54.25000000",
        "6.58959122"
      ],
      "h": [
        "54.25000000",
        "54.25000000"
      ],
      "l": [
        "50.30000000",
        "49.05000000"
      ],
      "o": "50.75000000",
      "p": [
        "52.70956654",
        "51.86521859"
      ],
      "t": [
        595,
        1439
      ],
      "v": [
        "3988.96212327",
        "10173.81558801"
      ]
    },
    "XXRPXXBT": {
      "a": [
        "0.000026030",
        "101",
        "101.000"
      ],
      "b": [
        "0.000026010",
        "2539",
        "2539.000"
      ],
      "c": [
        "0.000026080",
        "35.15064027"
      ],
      "h": [
        "0.000026400",
        "0.000026550"
      ],
      "l": [
        "0.000025900",
        "0.000025720"
      ],
      "o": "0.000026270",
      "p": [
        "0.000026075",
        "0.000000516"
      ],
      "t": [
        152,
        688
      ],
      "v": [
        "201994.07888234",
        "1192028.49997504"
      ]
    },
    "XXRPZEUR": {
      "a": [
        "0.16900000",
        "20972",
        "20972.000"
      ],
      "b": [
        "0.16899000",
        "12300",
        "12300.000"
      ],
      "c": [
        "0.16900000",
        "1831.99349112"
      ],
      "h": [
        "0.16900000",
        "0.17179000"
      ],
      "l": [
        "0.16392000",
        "0.16132000"
      ],
      "o": "0.16444000",
      "p": [
        "0.16649374",
        "0.16571573"
      ],
      "t": [
        1418,
        5716
      ],
      "v": [
        "6387073.29389055",
        "21490487.27225752"
      ]
    },
    "XXRPZUSD": {
      "a": [
        "0.18247000",
        "11441",
        "11441.000"
      ],
      "b": [
        "0.18246000",
        "3169",
        "3169.000"
      ],
      "c": [
        "0.18246000",
        "1831.99349112"
      ],
      "h": [
        "0.18250000",
        "0.18675000"
      ],
      "l": [
        "0.17780000",
        "0.17516000"
      ],
      "o": "0.17854000",
      "p": [
        "0.18011943",
        "0.17949282"
      ],
      "t": [
        689,
        3567
      ],
      "v": [
        "3470454.21323864",
        "16492402.19557948"
      ]
    },
    "XZECXXBT": {
      "a": [
        "0.004740",
        "31",
        "31.000"
      ],
      "b": [
        "0.004730",
        "17",
        "17.000"
      ],
      "c": [
        "0.004740",
        "0.03028064"
      ],
      "h": [
        "0.004780",
        "0.004810"
      ],
      "l": [
        "0.004700",
        "0.004670"
      ],
      "o": "0.004740",
      "p": [
        "0.004731",
        "-0.005337"
      ],
      "t": [
        73,
        226
      ],
      "v": [
        "233.37675196",
        "884.70475857"
      ]
    },
    "XZECZEUR": {
      "a": [
        "30.71600",
        "1",
        "1.000"
      ],
      "b": [
        "30.71000",
        "9",
        "9.000"
      ],
      "c": [
        "30.66200",
        "1.00000000"
      ],
      "h": [
        "30.66200",
        "31.05000"
      ],
      "l": [
        "29.61000",
        "28.79100"
      ],
      "o": "29.61000",
      "p": [
        "30.32441",
        "30.17642"
      ],
      "t": [
        128,
        659
      ],
      "v": [
        "843.75759550",
        "5405.01026473"
      ]
    },
    "XZECZUSD": {
      "a": [
        "33.18000",
        "21",
        "21.000"
      ],
      "b": [
        "33.10000",
        "12",
        "12.000"
      ],
      "c": [
        "32.97000",
        "0.23340000"
      ],
      "h": [
        "33.12000",
        "33.89000"
      ],
      "l": [
        "32.11000",
        "31.39000"
      ],
      "o": "32.20000",
      "p": [
        "32.81066",
        "32.65646"
      ],
      "t": [
        236,
        1037
      ],
      "v": [
        "1435.38402412",
        "4127.59066610"
      ]
    }
  }
}